[
    {
      "id": 1,
      "email": "hiss@gmail.com",
      "photo": "https://scontent-dfw5-1.xx.fbcdn.net/v/t1.0-9/55611013_1054876381387410_299583967579865088_n.jpg?_nc_cat=103&_nc_ht=scontent-dfw5-1.xx&oh=638d62fe74d540ec3b195fb8432dd467&oe=5D726648",
      "firstName": "Laila",
      "lastName": "F"
    },
    {
      "id": 2,
      "email": "oreo@instagram.com",
      "photo": "https://animalwellnessmagazine.com/wp-content/uploads/18581119_445885962441017_3995894352218947584_n-e1509563328874.jpg",
      "firstName": "Oreo",
      "lastName": "Cat"
    },
    {
      "id": 3,
      "email": "tabby@twitch.tv",
      "photo": "https://pbs.twimg.com/media/Cy32oI_WIAAbXZb.jpg:large",
      "firstName": "Tabby",
      "lastName": "MATN"
    }
   
  ]